githarbor/__init__.py
githarbor/__main__.py
githarbor/core/__init__.py
githarbor/core/base.py
githarbor/core/datatypes.py
githarbor/core/filechanges.py
githarbor/core/models.py
githarbor/core/proxy.py
githarbor/core/user_proxy.py
githarbor/exceptions.py
githarbor/functional.py
githarbor/mcp_server.py
githarbor/providers/__init__.py
githarbor/providers/aiogithubapi_provider/__init__.py
githarbor/providers/aiogithubapi_provider/owner.py
githarbor/providers/aiogithubapi_provider/repository.py
githarbor/providers/aiogithubapi_provider/utils.py
githarbor/providers/azure_provider/__init__.py
githarbor/providers/azure_provider/repository.py
githarbor/providers/azure_provider/utils.py
githarbor/providers/gitea_provider/__init__.py
githarbor/providers/gitea_provider/repository.py
githarbor/providers/gitea_provider/utils.py
githarbor/providers/github_provider/__init__.py
githarbor/providers/github_provider/owner.py
githarbor/providers/github_provider/repository.py
githarbor/providers/github_provider/utils.py
githarbor/providers/githubkit_provider/__init__.py
githarbor/providers/githubkit_provider/owner.py
githarbor/providers/githubkit_provider/repository.py
githarbor/providers/githubkit_provider/utils.py
githarbor/providers/gitlab_provider/__init__.py
githarbor/providers/gitlab_provider/repository.py
githarbor/providers/gitlab_provider/utils.py
githarbor/providers/local_provider/__init__.py
githarbor/providers/local_provider/repository.py
githarbor/providers/local_provider/utils.py
githarbor/py.typed
githarbor/registry.py
githarbor/repositories.py
githarbor/users.py
githarbor-1.0.0.dist-info/WHEEL
githarbor-1.0.0.dist-info/entry_points.txt
githarbor-1.0.0.dist-info/METADATA
githarbor-1.0.0.dist-info/RECORD
