Metadata-Version: 2.3
Name: githarbor
Version: 1.0.0
Summary: Unified client for GitHub, GitLab and BitBucket
Keywords: 
Author: Philipp Temminghoff
Author-email: Philipp Temminghoff <philipptemminghoff@googlemail.com>
License: MIT License
Classifier: Development Status :: 4 - Beta
Classifier: Intended Audience :: Developers
Classifier: Operating System :: OS Independent
Classifier: Programming Language :: Python :: 3
Classifier: Programming Language :: Python :: 3 :: Only
Classifier: Programming Language :: Python :: 3.12
Classifier: Programming Language :: Python :: 3.13
Classifier: Programming Language :: Python :: 3.14
Classifier: Topic :: Documentation
Classifier: Topic :: Software Development
Classifier: Topic :: Utilities
Classifier: Typing :: Typed
Requires-Dist: universal-pathlib
Requires-Dist: upathtools>=0.6.5
Requires-Dist: aiogithubapi ; extra == 'aiogithubapi'
Requires-Dist: pygithub ; extra == 'all'
Requires-Dist: python-gitlab ; extra == 'all'
Requires-Dist: atlassian-python-api ; extra == 'all'
Requires-Dist: giteapy ; extra == 'all'
Requires-Dist: azure-devops ; extra == 'all'
Requires-Dist: gitpython ; extra == 'all'
Requires-Dist: unidiff ; extra == 'all'
Requires-Dist: fastmcp ; extra == 'all'
Requires-Dist: azure-devops ; extra == 'azure'
Requires-Dist: atlassian-python-api ; extra == 'bitbucket'
Requires-Dist: unidiff ; extra == 'diff'
Requires-Dist: giteapy ; extra == 'gitea'
Requires-Dist: pygithub ; extra == 'github'
Requires-Dist: githubkit ; extra == 'githubkit'
Requires-Dist: python-gitlab ; extra == 'gitlab'
Requires-Dist: gitpython ; extra == 'local'
Requires-Dist: fastmcp ; extra == 'mcp'
Requires-Python: >=3.13
Project-URL: Code coverage, https://app.codecov.io/gh/phil65/githarbor
Project-URL: Discussions, https://github.com/phil65/githarbor/discussions
Project-URL: Documentation, https://phil65.github.io/githarbor/
Project-URL: Issues, https://github.com/phil65/githarbor/issues
Project-URL: Source, https://github.com/phil65/githarbor
Provides-Extra: aiogithubapi
Provides-Extra: all
Provides-Extra: azure
Provides-Extra: bitbucket
Provides-Extra: diff
Provides-Extra: gitea
Provides-Extra: github
Provides-Extra: githubkit
Provides-Extra: gitlab
Provides-Extra: local
Provides-Extra: mcp
